kriknn/__init__.py
kriknn/engine/__init__.py
kriknn/engine/tensor.py
kriknn/nn/__init__.py
kriknn/nn/context.py
kriknn/nn/optimizers.py
kriknn-0.1.3.dist-info/LICENSE
kriknn-0.1.3.dist-info/METADATA
kriknn-0.1.3.dist-info/WHEEL
kriknn-0.1.3.dist-info/top_level.txt
kriknn-0.1.3.dist-info/RECORD
