Metadata-Version: 2.1
Name: kriknn
Version: 0.1.3
Summary: KrikNN is a library that includes various components for neural network operations and tensor manipulations. This README provides an overview of the `Tensor` class and its functionality, as well as instructions for running the tests.
Home-page: https://github.com/andykr1k/kriknn
Author: Andrew Krikorian
License: MIT
Project-URL: Bug Reports, https://github.com/andykr1k/kriknn/issues
Project-URL: Source, https://github.com/andykr1k/kriknn
Classifier: License :: OSI Approved :: MIT License
Classifier: Operating System :: OS Independent
Requires-Python: >=3.8
License-File: LICENSE
Requires-Dist: numpy
